enhydris_cache/__init__.py
enhydris_cache/cli.py
enhydris_cache/enhydris_cache.py
enhydris_cache-2.0.0.dist-info/LICENSE
enhydris_cache-2.0.0.dist-info/METADATA
enhydris_cache-2.0.0.dist-info/WHEEL
enhydris_cache-2.0.0.dist-info/entry_points.txt
enhydris_cache-2.0.0.dist-info/top_level.txt
enhydris_cache-2.0.0.dist-info/RECORD
