Metadata-Version: 2.1
Name: enhydris-cache
Version: 2.0.0
Summary: Utilities for spatial integration of time series
Home-page: https://github.com/openmeteo/enhydris-cache
Author: Antonis Christofides
Author-email: antonis@antonischristofides.com
License: GNU General Public License v3
Keywords: enhydris-cache
Classifier: Development Status :: 4 - Beta
Classifier: Intended Audience :: Developers
Classifier: License :: OSI Approved :: GNU General Public License v3 (GPLv3)
Classifier: Natural Language :: English
Classifier: Programming Language :: Python :: 3.9
Classifier: Programming Language :: Python :: 3.10
Classifier: Programming Language :: Python :: 3.11
Classifier: Programming Language :: Python :: 3.12
License-File: LICENSE
Requires-Dist: Click >=7.0
Requires-Dist: enhydris-api-client <5,>=4
